example_four.py
example_one.py
example_three.py
example_two.py
mathchecker.py
pythonbasic.py
pythonbasic-0.1.0.dist-info/LICENSE.md
pythonbasic-0.1.0.dist-info/METADATA
pythonbasic-0.1.0.dist-info/WHEEL
pythonbasic-0.1.0.dist-info/top_level.txt
pythonbasic-0.1.0.dist-info/RECORD
