Metadata-Version: 2.1
Name: pythonbasic
Version: 0.1.0
Summary: A better way to program in TI-Basic
Author: DangItsPang
Project-URL: Homepage, https://github.com/dangitspang/pythonbasic
Project-URL: Issues, https://github.com/dangitspang/pythonbasic/issues
Classifier: Programming Language :: Python :: 3
Classifier: License :: OSI Approved :: MIT License
Classifier: Operating System :: OS Independent
Requires-Python: >=3.8
License-File: LICENSE.md
